NeuralPerk/NeuralPerk_Tensorflow.py
NeuralPerk/NeuralPerk_Torch.py
NeuralPerk/__init__.py
NeuralPerk-0.9.2.dist-info/METADATA
NeuralPerk-0.9.2.dist-info/WHEEL
NeuralPerk-0.9.2.dist-info/top_level.txt
NeuralPerk-0.9.2.dist-info/RECORD
