Metadata-Version: 2.1
Name: NeuralPerk
Version: 0.9.2
Summary: UNKNOWN
Home-page: UNKNOWN
License: UNKNOWN
Platform: UNKNOWN
Requires-Dist: pyqt5
Requires-Dist: requests
